astro_hipster-0.1.0.dist-info/licenses/LICENSE
hipster/__init__.py
hipster/absorption_line_plotter.py
hipster/hips_generator.py
hipster/html_generator.py
hipster/image_generator.py
hipster/image_plotter.py
hipster/inference.py
hipster/main.py
hipster/range.py
hipster/spectrum_plotter.py
hipster/task.py
hipster/votable_generator.py
hipster/wavelength_to_rgb.py
astro_hipster-0.1.0.dist-info/METADATA
astro_hipster-0.1.0.dist-info/WHEEL
astro_hipster-0.1.0.dist-info/entry_points.txt
astro_hipster-0.1.0.dist-info/top_level.txt
astro_hipster-0.1.0.dist-info/RECORD
