Metadata-Version: 2.4
Name: astro-hipster
Version: 0.1.0
Summary: Generate HiPS representation
Author-email: Kai Polsterer <kai.polsterer@h-its.org>, Bernd Doser <bernd.doser@h-its.org>, Andreas Fehlner <andreas.fehlner@h-its.org>, "Sebastian T. Gomez" <sebastian.trujillogomez@h-its.org>
License-Expression: Apache-2.0
Requires-Python: <4.0,>=3.10
License-File: LICENSE
Requires-Dist: astropy>=6.1
Requires-Dist: gaiaxpy>=2.1
Requires-Dist: healpy>=1.18
Requires-Dist: jsonargparse[omegaconf]>=4.37
Requires-Dist: matplotlib>=3.10
Requires-Dist: onnxruntime-gpu>=1.21
Requires-Dist: pandas>2.2
Requires-Dist: pyarrow>=20.0
Requires-Dist: scipy>1.15
Requires-Dist: tqdm>=4.67
Requires-Dist: jinja2>3.1
Requires-Dist: streamlit>=1.44
Provides-Extra: dev
Requires-Dist: ipykernel>=6.29; extra == "dev"
Requires-Dist: pytest>=8.3; extra == "dev"
Requires-Dist: ruff>=0.11; extra == "dev"
Dynamic: license-file
